[
  {
    "name": "Kithuka Gitonga Leonard",
    "ward": "NKONDI",
    "constituency": "Tharaka",
    "county": "Tharaka-Nithi",
    "seat_type": "mca",
    "party": "",
    "photo_url": "/photos/mcas/tharaka_nithi/nkondi.jpg",
    "nominated": false
  },
  {
    "name": "Marengo Luke Nyaga",
    "ward": "MUKOTHIMA",
    "constituency": "Tharaka",
    "county": "Tharaka-Nithi",
    "seat_type": "mca",
    "party": "",
    "photo_url": "/photos/mcas/tharaka_nithi/mukothima.jpg",
    "nominated": false
  },
  {
    "name": "Kiriko Jacob Ndeke",
    "ward": "MUGWE",
    "constituency": "Chuka/Igambang'Ombe",
    "county": "Tharaka-Nithi",
    "seat_type": "mca",
    "party": "",
    "photo_url": "/photos/mcas/tharaka_nithi/mugwe.jpg",
    "nominated": false
  },
  {
    "name": "Kabii Jones Kinegeni",
    "ward": "MWIMBI",
    "constituency": "Maara",
    "county": "Tharaka-Nithi",
    "seat_type": "mca",
    "party": "",
    "photo_url": "/photos/mcas/tharaka_nithi/mwimbi.jpg",
    "nominated": false
  },
  {
    "name": "Ntwiga Nevert",
    "ward": "MITHERU",
    "constituency": "Maara",
    "county": "Tharaka-Nithi",
    "seat_type": "mca",
    "party": "",
    "photo_url": "/photos/mcas/tharaka_nithi/mitheru.jpg",
    "nominated": false
  },
  {
    "name": "Anita Karimi Mbae",
    "ward": "MARIANI",
    "constituency": "Chuka/Igambang'Ombe",
    "county": "Tharaka-Nithi",
    "seat_type": "mca",
    "party": "",
    "photo_url": "/photos/mcas/tharaka_nithi/mariani.jpg",
    "nominated": false
  },
  {
    "name": "Nyaga Frankline Mawira",
    "ward": "CHOGORIA",
    "constituency": "Maara",
    "county": "Tharaka-Nithi",
    "seat_type": "mca",
    "party": "",
    "photo_url": "/photos/mcas/tharaka_nithi/chogoria.jpg",
    "nominated": false
  },
  {
    "name": "Gitonga Morris Maugu",
    "ward": "MUTHAMBI",
    "constituency": "Maara",
    "county": "Tharaka-Nithi",
    "seat_type": "mca",
    "party": "",
    "photo_url": "/photos/mcas/tharaka_nithi/muthambi.jpg",
    "nominated": false
  },
  {
    "name": "John Joseph Njeru",
    "ward": "IGAMBANG'OMBE",
    "constituency": "Chuka/Igambang'Ombe",
    "county": "Tharaka-Nithi",
    "seat_type": "mca",
    "party": "",
    "photo_url": "/photos/mcas/tharaka_nithi/igambang_ombe.jpg",
    "nominated": false
  },
  {
    "name": "Kamunyu Kennedy",
    "ward": "MARIMANTI",
    "constituency": "Tharaka",
    "county": "Tharaka-Nithi",
    "seat_type": "mca",
    "party": "",
    "photo_url": "/photos/mcas/tharaka_nithi/marimanti.jpg",
    "nominated": false
  },
  {
    "name": "Mbae Lysbeth Gateria",
    "ward": "GANGA",
    "constituency": "Maara",
    "county": "Tharaka-Nithi",
    "seat_type": "mca",
    "party": "",
    "photo_url": "/photos/mcas/tharaka_nithi/ganga.jpg",
    "nominated": false
  },
  {
    "name": "Njagi Joseph Kinyua",
    "ward": "CHIAKARIGA",
    "constituency": "Tharaka",
    "county": "Tharaka-Nithi",
    "seat_type": "mca",
    "party": "",
    "photo_url": "/photos/mcas/tharaka_nithi/chiakariga.jpg",
    "nominated": false
  },
  {
    "name": "Justin Kithinji Nderi",
    "ward": "MAGUMONI",
    "constituency": "Chuka/Igambang'Ombe",
    "county": "Tharaka-Nithi",
    "seat_type": "mca",
    "party": "",
    "photo_url": "/photos/mcas/tharaka_nithi/magumoni.jpg",
    "nominated": false
  },
  {
    "name": "Godfrey Murithi Muchiri",
    "ward": "KARINGANI",
    "constituency": "Chuka/Igambang'Ombe",
    "county": "Tharaka-Nithi",
    "seat_type": "mca",
    "party": "",
    "photo_url": "/photos/mcas/tharaka_nithi/karingani.jpg",
    "nominated": false
  },
  {
    "name": "Mugao Salvestas Kanyaru",
    "ward": "GATUNGA",
    "constituency": "Tharaka",
    "county": "Tharaka-Nithi",
    "seat_type": "mca",
    "party": "",
    "photo_url": "/photos/mcas/tharaka_nithi/gatunga.jpg",
    "nominated": false
  }
]